pypi_templates/__init__.py
pypi_templates/__main__.py
pypi_templates/__version__.py
pypi_templates/main.py
pypi_templates/package_data.dat
pypi_templates-0.1.8.dist-info/LICENSE
pypi_templates-0.1.8.dist-info/METADATA
pypi_templates-0.1.8.dist-info/WHEEL
pypi_templates-0.1.8.dist-info/entry_points.txt
pypi_templates-0.1.8.dist-info/top_level.txt
pypi_templates-0.1.8.dist-info/RECORD
